vr/__init__.py
vr/cli.py
vr.cli-4.2.dist-info/LICENSE
vr.cli-4.2.dist-info/METADATA
vr.cli-4.2.dist-info/WHEEL
vr.cli-4.2.dist-info/entry_points.txt
vr.cli-4.2.dist-info/top_level.txt
vr.cli-4.2.dist-info/RECORD
