Metadata-Version: 2.1
Name: vr.cli
Version: 4.2
Summary: Command-line client for Velociraptor
Home-page: https://github.com/yougov/vr.cli
Author: Jason R. Coombs
Author-email: jaraco@jaraco.com
License: UNKNOWN
Platform: UNKNOWN
Classifier: Development Status :: 5 - Production/Stable
Classifier: Intended Audience :: Developers
Classifier: License :: OSI Approved :: MIT License
Classifier: Programming Language :: Python :: 3
Classifier: Programming Language :: Python :: 3 :: Only
Requires-Python: >=3.5
Requires-Dist: jaraco.functools (>=1.0)
Requires-Dist: vr.common (>=6)
Requires-Dist: more-itertools
Requires-Dist: six
Requires-Dist: datadiff (>=1.1.6)
Requires-Dist: jaraco.ui (>=1.2)
Requires-Dist: tempora
Requires-Dist: jaraco.logging
Provides-Extra: docs
Requires-Dist: sphinx ; extra == 'docs'
Requires-Dist: jaraco.packaging (>=3.2) ; extra == 'docs'
Requires-Dist: rst.linker (>=1.9) ; extra == 'docs'
Provides-Extra: testing
Requires-Dist: pytest (!=3.7.3,>=3.5) ; extra == 'testing'
Requires-Dist: pytest-checkdocs ; extra == 'testing'
Requires-Dist: pytest-flake8 ; extra == 'testing'
